ai_trace/__init__.py
ai_trace/_version.py
ai_trace/trace_crewai.py
ai_trace/assets/__init__.py
ai_trace/assets/index.html
ai_trace-0.0.1.dist-info/licenses/LICENSE
ai_trace-0.0.1.dist-info/METADATA
ai_trace-0.0.1.dist-info/WHEEL
ai_trace-0.0.1.dist-info/top_level.txt
ai_trace-0.0.1.dist-info/RECORD
