Metadata-Version: 2.4
Name: ai-trace
Version: 0.0.1
Summary: Add your description here
Requires-Python: >=3.11
License-File: LICENSE
Dynamic: license-file
